bound/__init__.py
bound/bound.py
bound/tests/__init__.py
bound/tests/test_bound.py
bound/tests/test_data/test_hosts_format_data
bound-1.0.1.data/data/templates/test_hosts_format_data
bound-1.0.1.dist-info/AUTHORS
bound-1.0.1.dist-info/LICENSE
bound-1.0.1.dist-info/METADATA
bound-1.0.1.dist-info/WHEEL
bound-1.0.1.dist-info/entry_points.txt
bound-1.0.1.dist-info/pbr.json
bound-1.0.1.dist-info/top_level.txt
bound-1.0.1.dist-info/RECORD
